brunogge/__init__.py
brunogge/barony.py
brunogge/get_ws.py
brunogge/getconfig.py
brunogge/ggs_stuff.py
brunogge/just_funcs.py
brunogge/server_list.json
brunogge-0.1.9.dist-info/METADATA
brunogge-0.1.9.dist-info/WHEEL
brunogge-0.1.9.dist-info/top_level.txt
brunogge-0.1.9.dist-info/RECORD
